__init__.py
jupyter_omnicm/__init__.py
jupyter_omnicm/hdfs/__init__.py
jupyter_omnicm/hdfs/hdfs_checkpoints.py
jupyter_omnicm/hdfs/hdfs_io.py
jupyter_omnicm/hdfs/hdfs_manager.py
jupyter_omnicm-0.0.5.dist-info/AUTHORS.rst
jupyter_omnicm-0.0.5.dist-info/LICENSE
jupyter_omnicm-0.0.5.dist-info/METADATA
jupyter_omnicm-0.0.5.dist-info/WHEEL
jupyter_omnicm-0.0.5.dist-info/top_level.txt
jupyter_omnicm-0.0.5.dist-info/RECORD
